README.md
setup.py
pottok/__init__.py
pottok.egg-info/PKG-INFO
pottok.egg-info/SOURCES.txt
pottok.egg-info/dependency_links.txt
pottok.egg-info/not-zip-safe
pottok.egg-info/requires.txt
pottok.egg-info/top_level.txt
pottok/datasets/__init__.py
pottok/datasets/blackpottok.gpkg
pottok/datasets/blackpottok.jpg
pottok/datasets/blackpottok.tif
pottok/datasets/brownpottok.gpkg
pottok/datasets/brownpottok.jpg
pottok/datasets/brownpottok.tif
test/test_datasets.py
test/test_gridsearch.py
test/test_rot_vs_otgs.py
test/test_scale_rot.py