Metadata-Version: 2.1
Name: pottok
Version: 0.1rc1
Summary: Optimal Transport with raster image, including an optimal transport validation
Home-page: https://github.com/obernardoff/pottok/
Author: Olivia Bernardoff, Nicolas Karasiak, Yousra Hamrouni & David Sheeren
Author-email: olivia.bernardoff@outlook.fr
License: UNKNOWN
Platform: UNKNOWN
Classifier: Intended Audience :: Science/Research
Classifier: Programming Language :: Python :: 3
Requires-Python: >=3.5
